quda/cli/__init__.py
quda/cli/app.py
quda/cli/main.py
quda_cli-0.1.3.dist-info/METADATA
quda_cli-0.1.3.dist-info/WHEEL
quda_cli-0.1.3.dist-info/entry_points.txt
quda_cli-0.1.3.dist-info/top_level.txt
quda_cli-0.1.3.dist-info/RECORD
