Metadata-Version: 2.4
Name: quda-cli
Version: 0.1.3
License-Expression: MIT
Requires-Python: >=3.12
Requires-Dist: hydra-core>=1.3.2
Requires-Dist: quda-ml>=0.1.3
Requires-Dist: typer>=0.16.0
